{
  "version": 3,
  "middleware": {
    "/": {
      "files": [
        "prerender-manifest.js",
        "server/edge-runtime-webpack.js",
        "server/middleware.js"
      ],
      "name": "middleware",
      "page": "/",
      "matchers": [
        {
          "regexp": "^(?:\\/(_next\\/data\\/[^/]{1,}))?(?:\\/((?!api|public|.*\\..*|_next|favicon.ico|robots.txt).*))(.json)?[\\/#\\?]?$",
          "originalSource": "/((?!api|public|.*\\..*|_next|favicon.ico|robots.txt).*)"
        }
      ],
      "wasm": [],
      "assets": [],
      "environments": {
        "previewModeId": "dc19521104cbf094d50d13cc22ff1784",
        "previewModeSigningKey": "46f9ed78f6233db526b3914054e8bb58d000887a5572a7f88ae286246cff13c5",
        "previewModeEncryptionKey": "88d5a9a538b28b79373365a4367220bcad53564e2181f9ee2380e8fcd8e8e706"
      }
    }
  },
  "functions": {},
  "sortedMiddleware": [
    "/"
  ]
}